wrtc.cp310-win_amd64.pyd
webrtc/__init__.py
webrtc/base.py
webrtc/functions/__init__.py
webrtc/functions/get_user_media.py
webrtc/interfaces/__init__.py
webrtc/interfaces/media_stream.py
webrtc/interfaces/media_stream_track.py
webrtc/interfaces/rtc_audio_source.py
webrtc/interfaces/rtc_dtls_transport.py
webrtc/interfaces/rtc_ice_transport.py
webrtc/interfaces/rtc_peer_connection.py
webrtc/interfaces/rtc_rtp_receiver.py
webrtc/interfaces/rtc_rtp_sender.py
webrtc/interfaces/rtc_rtp_transceiver.py
webrtc/models/__init__.py
webrtc/models/rtc_on_data_event.py
webrtc/models/rtc_session_description.py
webrtc/models/rtc_session_description_init.py
webrtc/models/rtp_encoding_parameters.py
webrtc/models/rtp_transceiver_init.py
webrtc/utils/__init__.py
webrtc/utils/callbacks_to_async.py
webrtc/utils/convert_exceptions.py
wrtc-0.0.0.dev9.dist-info/LICENSE.md
wrtc-0.0.0.dev9.dist-info/METADATA
wrtc-0.0.0.dev9.dist-info/WHEEL
wrtc-0.0.0.dev9.dist-info/top_level.txt
wrtc-0.0.0.dev9.dist-info/RECORD
