Metadata-Version: 2.1
Name: wrtc
Version: 0.0.0.dev9
Summary: a Python extension that provides bindings to WebRTC M92
Home-page: https://github.com/MarshalX/python-webrtc
Author: Il`ya Semyonov
Author-email: ilya@marshal.dev
License: BSD 3-Clause
Project-URL: Author, https://github.com/MarshalX
Project-URL: Tracker, https://github.com/MarshalX/python-webrtc/issues
Project-URL: Source, https://github.com/MarshalX/python-webrtc
Platform: UNKNOWN
Classifier: Development Status :: 1 - Planning
Classifier: Natural Language :: English
Classifier: Intended Audience :: Developers
Classifier: License :: OSI Approved :: BSD License
Classifier: Operating System :: OS Independent
Classifier: Operating System :: MacOS
Classifier: Operating System :: Unix
Classifier: Topic :: Internet
Classifier: Topic :: Multimedia
Classifier: Topic :: Multimedia :: Video
Classifier: Topic :: Multimedia :: Video :: Capture
Classifier: Topic :: Multimedia :: Sound/Audio
Classifier: Topic :: Multimedia :: Sound/Audio :: Capture/Recording
Classifier: Topic :: Communications
Classifier: Topic :: Communications :: Internet Phone
Classifier: Topic :: Communications :: Telephony
Classifier: Topic :: Software Development :: Libraries
Classifier: Topic :: Software Development :: Libraries :: Python Modules
Classifier: Programming Language :: C++
Classifier: Programming Language :: Python
Classifier: Programming Language :: Python :: 3
Classifier: Programming Language :: Python :: 3 :: Only
Classifier: Programming Language :: Python :: 3.7
Classifier: Programming Language :: Python :: 3.8
Classifier: Programming Language :: Python :: 3.9
Classifier: Programming Language :: Python :: 3.10
Classifier: Programming Language :: Python :: Implementation
Classifier: Programming Language :: Python :: Implementation :: CPython
Requires-Python: ~=3.7
License-File: LICENSE.md
